helpo/.gitignore
helpo/__init__.py
helpo/cloudflare.py
helpo/cloudflarecmd.py
helpo/dedibox.py
helpo/dediboxcmd.py
helpo/jira.py
helpo/jiracmd.py
helpo/main.py
helpo/namedotcom.py
helpo/namedotcomcmd.py
helpo/remoteserver.py
helpo/remoteservercmd.py
helpo/rundeckjobs.py
helpo/rundeckjobscmd.py
helpo-0.4.16.dist-info/METADATA
helpo-0.4.16.dist-info/WHEEL
helpo-0.4.16.dist-info/entry_points.txt
helpo-0.4.16.dist-info/RECORD
