Metadata-Version: 2.1
Name: helpo
Version: 0.4.16
Summary: zg helper cli scripts
License: Proprietary
Author: Ahmed Kamel
Author-email: ahmedk@zadgroup.net
Requires-Python: >=3.8,<4.0
Classifier: License :: Other/Proprietary License
Classifier: Programming Language :: Python :: 3
Classifier: Programming Language :: Python :: 3.8
Classifier: Programming Language :: Python :: 3.9
Classifier: Programming Language :: Python :: 3.10
Classifier: Programming Language :: Python :: 3.11
Classifier: Programming Language :: Python :: 3.12
Requires-Dist: atlassian-python-api (>=3.10.0,<4.0.0)
Requires-Dist: cloudflare (>=2.8.15,<3.0.0)
Requires-Dist: hvac (>=0.11.2,<0.12.0)
Requires-Dist: jsonmerge (>=1.8.0,<2.0.0)
Requires-Dist: loguru (>=0.5.3,<0.6.0)
Requires-Dist: minio (>=7.0.3,<8.0.0)
Requires-Dist: namecom (>=0.5.0,<0.6.0)
Requires-Dist: packaging (>=21.3,<22.0)
Requires-Dist: requests (>=2.25.1,<3.0.0)
Requires-Dist: slumber (>=0.7.1,<0.8.0)
Requires-Dist: tenacity (>=8.0.1,<9.0.0)
Requires-Dist: tldextract (>=3.1.2,<4.0.0)
Requires-Dist: typer (>=0.4.0,<0.5.0)
Requires-Dist: zxpy (>=1.2.2,<2.0.0)
